{
  "startDate": "",
  "endDate": "",
  "gagnants1": [],
  "gagnants2": [],
  "gagnants3": [],
  "gagnants4": [],
  "gagnants5": [],
  "gagnants6": [],
  "links": {
    "siteLotGagnant1": "https://sms.link/",
    "siteLotGagnant2": "https://sms.link/",
    "siteLotGagnant3": "https://sms.link/",
    "siteLotGagnant4": "https://sms.link/",
    "siteLotGagnant5": "https://sms.link/",
    "siteLotGagnant6": "https://sms.link/",
    "sitePerdant": "https://sms.link/",
    "siteFinJeu": "https://sms.link/"
  }
}